tharospytools/__init__.py
tharospytools/bio_tools.py
tharospytools/console_utilities.py
tharospytools/data_structures.py
tharospytools/list_tools.py
tharospytools/logging_tools.py
tharospytools/matplotlib_tools.py
tharospytools/multithreading.py
tharospytools/overloading.py
tharospytools/path_tools.py
tharospytools/signatures.py
tharos_pytools-0.0.32.dist-info/LICENCE
tharos_pytools-0.0.32.dist-info/METADATA
tharos_pytools-0.0.32.dist-info/WHEEL
tharos_pytools-0.0.32.dist-info/top_level.txt
tharos_pytools-0.0.32.dist-info/RECORD
