Metadata-Version: 2.1
Name: tharos-pytools
Version: 0.0.32
Summary: Collection of quality-of-life functions
Home-page: https://github.com/Tharos-ux/tharos-pytools
Author: ('Tharos',)
Author-email: Tharos <dubois.siegfried@gmail.com>
Project-URL: Homepage, https://github.com/Tharos-ux/tharos-pytools
Project-URL: Bug Tracker, https://github.com/Tharos-ux/tharos-pytools/issues
Classifier: Programming Language :: Python :: 3
Classifier: License :: OSI Approved :: MIT License
Classifier: Operating System :: OS Independent
Requires-Python: >=3.10
License-File: LICENCE
